Workbook

Sheet Formato Syllabus
C2: FORMATO | I2: Versión: 0
I3: Código: IAC-201-f1
B4: SYLLABUS | I4: Fecha:16/Sep/2025
B6: 1. Información General de la Unidad de Estudio
B7: Año | D7: Código Plan de estudios | F7: Código Unidad de Estudio | H7: Tipo Unidad de estudio
B8: Facultad o Área | D8: Programa | G8: Nombre Unidad de estudios
B9: Créditos Académicos | D9: HAD | F9: HTA | H9: HT | I9: =E9+G9 -> 0
B10: 2. Modalidad y Metodología
B11: Seleccione con una X la modalidad en la que se desarrolla la Unidad. | D11: Presencial | G11: Virtual
B13: Metodología (Aplica solo para unidades de estudio de la modalidad presencial)
B14: PAT | E14: In Situ | G14: Híbrida
B15: 3. Propósito, Competencias y Resultados de Aprendizaje.
B16: Propósito de la Unidad de Estudio
B18: Competencia de Programa
B19: Resultado de Aprendizaje de Programa
B21: Resultado de Aprendizaje Unidad de Estudio
B23: Criterios de evaluación | D23: 1.
D24: 2.
D25: 3.
D26: 4.
B27: Competencias del modelo educativo a desarrollar (Seleccione con X aquellas competencias del modelo educativo que se desarrollarán en la Unidad de Estudio). | D27: EM | F27: SH | H27: IN
D28: COM | F28: SO | H28: AA
D29: SE | F29: COL | H29: DI
B30: *Las competencias corresponden a: EM: Emprendedoras, SH: Socio-humanísticas, IN: Investigativas, COM: Comunicativas, SO: Sostenibilidad, AA: Aprendizaje Autónomo, SE: Socio Emocionales, COL: Colaborativas, DI: Digitales.
B35: 4. Contenidos y Estrategias Pedagógicas
B36: En este apartado se solicita diligenciar los temas que harán parte de los contenidos de la UE; En cuanto a las estrategias pedagógicas relacionar los métodos, técnicas o acciones planificadas que se utilizan para facilitar el proceso de enseñanza-aprendizaje.
B39: Contenidos Unidad de estudio: | F39: Estrategias Pedagógicas:
B48: 5. Esquema de Calificación, Recursos y Componente de Lengua Extranjera
B49: Esquema de Calificación: (Asignación puntajes, notas y ponderación que tienen las actividades desarrolladas en la Unidad de Estudio). | F49: Recursos Tecnológicos
B60: Componente de Lengua extranjera | H60: Porcentaje
B65: 6. Bibliografía Obligatoria y Complementaria.
B66: Bibliografía Obligatoria | F66: Bibliografía Complementaria
B81: 7. Control de Cambios
B82: # versión | C82: Fecha | D82: Elaoró | E82: Revisó | F82: Aprobó | G82: Descripción del cambio

Sheet Formato Syllabus_NV
C2: FORMATO | I2: Versión: 0
I3: Código: IAC-201-f1
B4: SYLLABUS | I4: Fecha:16/Sep/2025
B6: 1. Información General de la Unidad de Estudio
B7: Año | D7: Código Plan de estudios | F7: Código Unidad de Estudio | H7: Tipo Unidad de estudio
B8: Facultad o Área | D8: Programas | G8: Nombre Unidad de estudios | K8: Agrehar posgrado pregrado
B9: Créditos Académicos | C9: 3 | D9: HAD | E9: 54 | F9: HTA | G9: 90 | H9: HT | I9: =E9+G9 -> 144 | K9: Tenr claro quienes van a responder por esas coordinaciones
B10: 2. Modalidad y Metodología
B11: Seleccione con una X la modalidad en la que se desarrolla la Unidad. | D11: Presencial | G11: Virtual
B13: Metodología (Aplica solo para unidades de estudio de la modalidad presencial)
B14: PAT | E14: In Situ | G14: Híbrida
B15: 3. Propósito, Competencias y Resultados de Aprendizaje.
B16: Propósito de la Unidad de Estudio | D16: descripción delcurso
B18: Competencia de Programa
B19: Resultado de Aprendizaje de Programa
B21: Resultado de Aprendizaje Unidad de Estudio | D21: matriz
B23: Criterios de evaluación | D23: 1.
D24: 2.
D25: 3.
D26: 4.
B27: Competencias del modelo educativo a desarrollar alinear como casilla y dejar descripción pie de pagina | D27: Emprendimiento Sostenible | G27: Liderar procesos emprendedores e innovadores para crear o transformar organizaciones y entornos hacia la sostenibilidad, generando valor en contextos diversos e inciertos. | L27: cargar los ysllabus de cinco años anteriores
D28: Power Humanise | G28: Integrar pensamiento crítico, empatía, diseño centrado en las personas y criterios éticos y sostenibles para crear soluciones, relaciones y acciones que promuevan bienestar, propósito y valor colectivo. | L28: Oferta actual a 2026 - 1
D29: TECH IA MAKER | G29: Utilizar la IA de manera ética, crítica y estratégica para potenciar capacidades humanas, resolver problemas, crear soluciones, optimizar procesos y generar valor. | L29: Solicitar a los profesores comité curricular antes
B30: 4. Contenidos y Estrategias Pedagógicas
B31: En este apartado se solicita diligenciar los temas que harán parte de los contenidos de la UE; En cuanto a las estrategias pedagógicas relacionar los métodos, técnicas o acciones planificadas que se utilizan para facilitar el proceso de enseñanza-aprendizaje.
B34: Contenidos Unidad de estudio: dar tipologia 4.5 semanas, 9 semanas y 18 semanas | F34: Estrategias Pedagógicas:
B43: 5. Esquema de Calificación, Recursos y Componente de Lengua Extranjera
B44: Esquema de Calificación: (Asignación puntajes, notas y ponderación que tienen las actividades desarrolladas en la Unidad de Estudio). Redactar en evaluación de impacto, meter con las competencia emprendimiento sostebible, power humanise o ia tech maker | F44: Recursos Tecnológicos reorganizar
B55: Componente de Lengua extranjera solo inglés | F55: Inglés | H55: Porcentaje
B60: 6. Bibliografía Obligatoria y Complementaria.
B61: Bibliografía Obligatoria | F61: Bibliografía Complementaria
B76: 7. Control de Cambios
B77: # versión | C77: Fecha | D77: Elaoró | E77: Revisó | F77: Aprobó | G77: Descripción del cambio

Sheet Hoja1
H3: Información Extraída
B4: 1 | C4: Año | D4: 2026 | H4: 2026
B5: 2 | C5: Código Plan de estudios | D5: PFVINIBOG002 | H5: PFVINIBOG002
B6: 3 | C6: Código Unidad de Estudio | D6: IFVN0011 | H6: IFVN0011
B7: 4 | C7: Tipo Unidad de estudio | D7: =+H7 -> Nuclear | H7: Nuclear
B8: 5 | C8: Facultad o Área | D8: =+H8 -> Facultad de Ingeniería | H8: Facultad de Ingeniería
B9: 6 | C9: Programa | D9: =+H9 -> Ingeniería Industrial | H9: Ingeniería Industrial
B10: 7 | C10: Nombre Unidad de estudios | D10: =+H10 -> Factores humanos y organización | H10: Factores humanos y organización
B11: 8 | C11: Créditos Académicos | D11: 3 | H11: 3
B12: 9 | C12: HAD | D12: =+H12 -> 54 | H12: 54
B13: 10 | C13: HTA | D13: =+H13 -> 90 | H13: 90
B14: 11 | C14: HT | D14: =+H14 -> 144 | H14: 144
B15: 12 | C15: Modalidad (Presencial / Virtual) | D15: =+H15 -> VIRTUAL | E15: =IF(D15="Presencial","SI","") | F15: =IF(D15="Virtual","SI","") -> SI | H15: VIRTUAL
B16: 13 | C16: Metodología (PAT / In Situ / Híbrida) | D16: =+H16 -> Aprendizaje basado en retos, Aprendizaje basado en proyectos, Aprendizaje basado en caso de estudio, Aprendizaje experiencial, Aprendizaje basado en problemas, Aprendizaje basado en investigación | H16: Aprendizaje basado en retos, Aprendizaje basado en proyectos, Aprendizaje basado en caso de estudio, Aprendizaje experiencial, Aprendizaje basado en problemas, Aprendizaje basado en investigación
B17: 14 | C17: Propósito de la Unidad de Estudio | D17: =+H17 -> Proporcionar una comprensión profunda de la interacción entre los seres humanos y los sistemas de trabajo para diseñar entornos productivos, seguros y ergonómicos. | H17: Proporcionar una comprensión profunda de la interacción entre los seres humanos y los sistemas de trabajo para diseñar entornos productivos, seguros y ergonómicos.
B18: 15 | C18: Competencia de Programa | D18: =+H18 -> No se especifica una competencia general de programa independiente en el texto. | H18: No se especifica una competencia general de programa independiente en el texto.
B19: 16 | C19: Resultado de Aprendizaje de Programa | D19: =+H19 -> No se detalla un resultado específico de nivel programa en el documento. | H19: No se detalla un resultado específico de nivel programa en el documento.
B20: 17 | C20: Resultado de Aprendizaje de la Unidad de Estudio | H20: Diseñar y optimizar sistemas de trabajo integrales considerando capacidades humanas, ergonomía y estructura organizacional para mejorar bienestar y productividad.
B21: 18 | C21: Criterios de evaluación (1, 2, 3, 4) | H21: 1. Realización de lecturas que motiven la reflexión de los temas tratados en el módulo. 2. Prueba individual de conocimiento. 3. Avance N.1 del proyecto integrador. 4. Avance N.2 del proyecto integrador. 5. Avance N.3 del proyecto integrador. 6. Proyecto integrador final. 7. Prueba en línea Unidad de estudio.
B22: 19 | C22: Competencias del modelo educativo (EM, SH, IN, COM, SO, AA, SE, COL, DI) | H22: EM, SH, IN, CO, SO, AU, SE, COL, DI.
B23: 20 | C23: Contenidos de la Unidad de estudio | D23: 9 Semanas | E23: =IF(D23="4.5 Semanas",H23,"") | F23: =IF(D23="9 Semanas",H23,"") -> Módulo 1: Talento Humano y Diseño Organizacional 1. La contribución del Talento Humano como eje vital de la Organización. 2. Tendencias globales que impactan la Gestión Humana y su relación con el Diseño Organizacional. 3. Planeación del Talento Humano para la Organización: 3.1 Aspectos que influyen en la proyección de necesidades de Talento Humano. 3.2. Diseño Ocupacional: Estructura organizacional y análisis y descripción de cargos. Módulo 2: Adquisición, Desarrollo y Retención del Talento 1. La Gestión Humana responsable de impulsar el ciclo de vida del talento en la Organización. 2. Adquisición del Talento: 2.1 Estrategias de Atracción, 2.2 Proceso de reclutamiento y Selección, 2.3 Proceso de Vinculación y Contratación. 3. Desarrollo: 3.1 Onboarding, 3.2 Plan de Carrera, 3.3 Formación y Entrenamiento. 4. Otras estrategias que contribuyen a la Retención: 4.1 Sistemas de Compensación, 4.2 Reconocimiento y Recompensa, 4.3 Creación de ambientes de trabajo positivos para la productividad y el bienestar. 5. Desvinculación Laboral: outplacement como estrategia clave. Módulo 3: Resultados Sostenibles de la Gestión Humana en la Organización 1. El vínculo entre la Gestión del Desempeño y la Satisfacción Laboral. 2. La retroalimentación y la evaluación del desempeño. 3. La medición del clima laboral. 4. Las métricas de la Gestión del Talento Humano. | G23: =IF(D23="18 Semanas",H23,"") | H23: Módulo 1: Talento Humano y Diseño Organizacional 1. La contribución del Talento Humano como eje vital de la Organización. 2. Tendencias globales que impactan la Gestión Humana y su relación con el Diseño Organizacional. 3. Planeación del Talento Humano para la Organización: 3.1 Aspectos que influyen en la proyección de necesidades de Talento Humano. 3.2. Diseño Ocupacional: Estructura organizacional y análisis y descripción de cargos. Módulo 2: Adquisición, Desarrollo y Retención del Talento 1. La Gestión Humana responsable de impulsar el ciclo de vida del talento en la Organización. 2. Adquisición del Talento: 2.1 Estrategias de Atracción, 2.2 Proceso de reclutamiento y Selección, 2.3 Proceso de Vinculación y Contratación. 3. Desarrollo: 3.1 Onboarding, 3.2 Plan de Carrera, 3.3 Formación y Entrenamiento. 4. Otras estrategias que contribuyen a la Retención: 4.1 Sistemas de Compensación, 4.2 Reconocimiento y Recompensa, 4.3 Creación de ambientes de trabajo positivos para la productividad y el bienestar. 5. Desvinculación Laboral: outplacement como estrategia clave. Módulo 3: Resultados Sostenibles de la Gestión Humana en la Organización 1. El vínculo entre la Gestión del Desempeño y la Satisfacción Laboral. 2. La retroalimentación y la evaluación del desempeño. 3. La medición del clima laboral. 4. Las métricas de la Gestión del Talento Humano.
B24: 21 | C24: Estrategias Pedagógicas | H24: Realización de lecturas reflexivas, pruebas individuales de conocimiento, desarrollo de proyecto integrador por avances, aprendizaje basado en retos, proyectos, casos de estudio, experiencial, problemas e investigación.
B25: 22 | C25: Esquema de Calificación | D25: =+H25 -> Guía (Fase) 1: 15%; Guía (Fase) 2: 25%; Guía (Fase) 3: 15%; Proyecto integrador: 30%; Prueba en línea Unidad de estudio: 15%. | H25: Guía (Fase) 1: 15%; Guía (Fase) 2: 25%; Guía (Fase) 3: 15%; Proyecto integrador: 30%; Prueba en línea Unidad de estudio: 15%.
B26: 23 | C26: Recursos Tecnológicos | D26: =+H26 -> 1. Plataforma de aprendizaje en línea. 2. Bases de datos de la biblioteca. 3. Software de gestión de recursos humanos. 4. Herramientas de análisis de datos. | H26: 1. Plataforma de aprendizaje en línea. 2. Bases de datos de la biblioteca. 3. Software de gestión de recursos humanos. 4. Herramientas de análisis de datos.
B27: 24 | C27: Componente de Lengua Extranjera | D27: =+H27 -> Ingles | H27: Ingles
B28: 25 | C28: Porcentaje | D28: =+H28 -> 0.2 | H28: 0.2
B29: 26 | C29: Bibliografía Obligatoria | D29: =+H29 -> Arroyo Tovar, R. (2022). Habilidades Gerenciales : desarrollo de destrezas, competencias y actitud (3a edición.). Ecoe Ediciones. Castillo Aponte, J. Gestión humana integral. La previsión de la fuerza laboral. Ecoe Ediciones, 2020. pp.23 - 36 https://elibro-net.bdbiblioteca.universidadean.edu.co/es/ereader/bibliotecaeanecoe/129215?page=5. Chiavenato, I. (2020). Evaluación de la gestión del talento humano .En Gestión del talento humano: el nuevo papel de los recursos humanos en las organizaciones. (5ª ed., pp. 447 -469) . McGraw-Hill. http://www-ebooks7-24-com.bdbiblioteca.universidadean.edu.co/stage.aspx?il=9350&pg=&ed= Huang, L., Chen, Y., & Wang, J. (2025). Prácticas estratégicas de recursos humanos impulsadas por ESG: Transformación de la gestión de empleados para un crecimiento organizacional sostenible. Cornell University. arXiv. https://arxiv.org/abs/2505.08201 Suárez, P. (2025). Organizaciones basadas en habilidades: el nuevo modelo de gestión del talento humano. Revista Recursos Humanos. https://revistarecursoshumanos.com/gestiontalento/organizaciones-basadas-en-habilidades-el-nuevo-modelo-de-gestion-del-talento-humano/ | E29: =CONCATENATE("Bibliografía Obligatoria",": ",D29) -> Bibliografía Obligatoria: Arroyo Tovar, R. (2022). Habilidades Gerenciales : desarrollo de destrezas, competencias y actitud (3a edición.). Ecoe Ediciones. Castillo Aponte, J. Gestión humana integral. La previsión de la fuerza laboral. Ecoe Ediciones, 2020. pp.23 - 36 https://elibro-net.bdbiblioteca.universidadean.edu.co/es/ereader/bibliotecaeanecoe/129215?page=5. Chiavenato, I. (2020). Evaluación de la gestión del talento humano .En Gestión del talento humano: el nuevo papel de los recursos humanos en las organizaciones. (5ª ed., pp. 447 -469) . McGraw-Hill. http://www-ebooks7-24-com.bdbiblioteca.universidadean.edu.co/stage.aspx?il=9350&pg=&ed= Huang, L., Chen, Y., & Wang, J. (2025). Prácticas estratégicas de recursos humanos impulsadas por ESG: Transformación de la gestión de empleados para un crecimiento organizacional sostenible. Cornell University. arXiv. https://arxiv.org/abs/2505.08201 Suárez, P. (2025). Organizaciones basadas en habilidades: el nuevo modelo de gestión del talento humano. Revista Recursos Humanos. https://revistarecursoshumanos.com/gestiontalento/organizaciones-basadas-en-habilidades-el-nuevo-modelo-de-gestion-del-talento-humano/ | H29: Arroyo Tovar, R. (2022). Habilidades Gerenciales : desarrollo de destrezas, competencias y actitud (3a edición.). Ecoe Ediciones. Castillo Aponte, J. Gestión humana integral. La previsión de la fuerza laboral. Ecoe Ediciones, 2020. pp.23 - 36 https://elibro-net.bdbiblioteca.universidadean.edu.co/es/ereader/bibliotecaeanecoe/129215?page=5. Chiavenato, I. (2020). Evaluación de la gestión del talento humano .En Gestión del talento humano: el nuevo papel de los recursos humanos en las organizaciones. (5ª ed., pp. 447 -469) . McGraw-Hill. http://www-ebooks7-24-com.bdbiblioteca.universidadean.edu.co/stage.aspx?il=9350&pg=&ed= Huang, L., Chen, Y., & Wang, J. (2025). Prácticas estratégicas de recursos humanos impulsadas por ESG: Transformación de la gestión de empleados para un crecimiento organizacional sostenible. Cornell University. arXiv. https://arxiv.org/abs/2505.08201 Suárez, P. (2025). Organizaciones basadas en habilidades: el nuevo modelo de gestión del talento humano. Revista Recursos Humanos. https://revistarecursoshumanos.com/gestiontalento/organizaciones-basadas-en-habilidades-el-nuevo-modelo-de-gestion-del-talento-humano/
B30: 27 | C30: Bibliografía Complementaria | D30: =+H30 -> Adaptación digital y cuidado del talento. (2024). Revista Gestión Humana. Deloitte. (2025). Tendencias Globales de Capital Humano 2025. Recursos humanos, fuerza laboral y tendencias en el lugar de trabajo del futuro. Blog Comercial Deloitte. http/www.deloitte.com/latam/es/services/consulting/research/tendencias-globales-de-capital-humano-2025.html Judge, T. A., Piccolo, R. F., Podsakoff, N. P., Shaw, J. C., & Rich, B. L. (2010). La relación entre el salario y la satisfacción laboral: un metaanálisis de la literatura. Journal of Vocational Behavior, 77(2), 157–167. https://doi.org/10.1016/j.jvb.2010.04.002 ManpowerGroup. (2023). Escasez de talento 2023. ManpowerGroup. https://www.manpowergroup.com/ Parra, J. M., Torres, C., & Herrera Sarmiento, E. (2023). ¿Por qué perdemos talento? : cómo gestionar el journey de los colaboradores en la empresa (1a edición.). Ediciones de la U. Pujol-Cols, L. & Lazzaro-Salazar, M. (2022). Gestión de la diversidad en el trabajo. Universidad del Sur (Ed.) Administración de recursos humanos: perspectiva académica y práctica profesional (Edición N.1, pp.155-157). Ediuns. https://www.researchgate.net/publication/365318675_Gestion_de_la_diversidad_en_el_trabajo | E30: =CONCATENATE("Bibliografía Complementaria",": ",D30) -> Bibliografía Complementaria: Adaptación digital y cuidado del talento. (2024). Revista Gestión Humana. Deloitte. (2025). Tendencias Globales de Capital Humano 2025. Recursos humanos, fuerza laboral y tendencias en el lugar de trabajo del futuro. Blog Comercial Deloitte. http/www.deloitte.com/latam/es/services/consulting/research/tendencias-globales-de-capital-humano-2025.html Judge, T. A., Piccolo, R. F., Podsakoff, N. P., Shaw, J. C., & Rich, B. L. (2010). La relación entre el salario y la satisfacción laboral: un metaanálisis de la literatura. Journal of Vocational Behavior, 77(2), 157–167. https://doi.org/10.1016/j.jvb.2010.04.002 ManpowerGroup. (2023). Escasez de talento 2023. ManpowerGroup. https://www.manpowergroup.com/ Parra, J. M., Torres, C., & Herrera Sarmiento, E. (2023). ¿Por qué perdemos talento? : cómo gestionar el journey de los colaboradores en la empresa (1a edición.). Ediciones de la U. Pujol-Cols, L. & Lazzaro-Salazar, M. (2022). Gestión de la diversidad en el trabajo. Universidad del Sur (Ed.) Administración de recursos humanos: perspectiva académica y práctica profesional (Edición N.1, pp.155-157). Ediuns. https://www.researchgate.net/publication/365318675_Gestion_de_la_diversidad_en_el_trabajo | H30: Adaptación digital y cuidado del talento. (2024). Revista Gestión Humana. Deloitte. (2025). Tendencias Globales de Capital Humano 2025. Recursos humanos, fuerza laboral y tendencias en el lugar de trabajo del futuro. Blog Comercial Deloitte. http/www.deloitte.com/latam/es/services/consulting/research/tendencias-globales-de-capital-humano-2025.html Judge, T. A., Piccolo, R. F., Podsakoff, N. P., Shaw, J. C., & Rich, B. L. (2010). La relación entre el salario y la satisfacción laboral: un metaanálisis de la literatura. Journal of Vocational Behavior, 77(2), 157–167. https://doi.org/10.1016/j.jvb.2010.04.002 ManpowerGroup. (2023). Escasez de talento 2023. ManpowerGroup. https://www.manpowergroup.com/ Parra, J. M., Torres, C., & Herrera Sarmiento, E. (2023). ¿Por qué perdemos talento? : cómo gestionar el journey de los colaboradores en la empresa (1a edición.). Ediciones de la U. Pujol-Cols, L. & Lazzaro-Salazar, M. (2022). Gestión de la diversidad en el trabajo. Universidad del Sur (Ed.) Administración de recursos humanos: perspectiva académica y práctica profesional (Edición N.1, pp.155-157). Ediuns. https://www.researchgate.net/publication/365318675_Gestion_de_la_diversidad_en_el_trabajo
B31: 28 | C31: Número de versión | D31: =+H31 -> 1 | H31: 1
B32: 29 | C32: Fecha | D32: =+H32 -> 45884 | H32: 45884
B33: 30 | C33: Elaboró | D33: =+H33 -> SANDRA XIMENA DIAZ | H33: SANDRA XIMENA DIAZ
B34: 31 | C34: Revisó | D34: =+H34 -> JOSE DIVITT VELOSA | H34: JOSE DIVITT VELOSA
B35: 32 | C35: Aprobó | D35: Jose Divitt Velosa | H35: JEFFREY LEÓN
B36: 33 | C36: Descripción del cambio | D36: =+H36 -> NUEVA MALLA | H36: NUEVA MALLA

Sheet Formato Syllabus_NV (2)
C2: FORMATO | I2: Versión: 1
I3: Código: IAC-201-f1
B4: SYLLABUS | I4: Fecha: 17/Feb/2026
B6: 1. Información General de la Unidad de Estudio
B7: Año | C7: =+Hoja1!D4 -> 2026 | D7: Código Plan de estudios | E7: =+Hoja1!D5 -> PFVINIBOG002 | F7: Código Unidad de Estudio | G7: =+Hoja1!D6 -> IFVN0011 | H7: Tipo Unidad de estudio | I7: =+Hoja1!D7 -> Nuclear
B8: Modalidad | C8: Presencial | D8: =+Hoja1!E15 | E8: Virtual | F8: =+Hoja1!F15 -> SI | G8: Presencial y Virtual
B9: Nivel | C9: Pregrado | D9: Programas | E9: =+Hoja1!D9 -> Ingeniería Industrial | G9: Nombre Unidad de estudios | H9: =+Hoja1!D10 -> Factores humanos y organización
B10: Créditos Académicos | C10: =+Hoja1!D11 -> 3 | D10: HAD | E10: =+Hoja1!D12 -> 54 | F10: HTA | G10: =+Hoja1!D13 -> 90 | H10: HT | I10: =E10+G10 -> 144
B11: 2. Descripción Resultados de Aprendizaje.
B12: Descripción de la unidad de estudio | D12: =+Hoja1!D17 -> Proporcionar una comprensión profunda de la interacción entre los seres humanos y los sistemas de trabajo para diseñar entornos productivos, seguros y ergonómicos.
B13: Resultado de Aprendizaje | D13: Estructura sistemas de gestión de operación y logística, para la producción de bienes o servicios mediante las prácticas analíticas, computacionales y experimentales apropiadas, de manera eficaz, eficiente, sostenible y socialmente responsable.
B14: 3. Contenidos
B15: En este apartado se solicita diligenciar los temas que harán parte de los contenidos de la UE teniendo en cuenta si la unidad se desarrolla de Ciclo, Módulo o Semestre
B18: Contenidos Unidad de estudio: dar tipología 4.5 semanas, 9 semanas y 18 semanas
B19: Módulo | C19: 4.5 Semanas | D19: Ciclo | E19: 9 Semanas | G19: Semestre | H19: 18 Semanas
B20: =+Hoja1!E23 | D20: =+Hoja1!F23 -> Módulo 1: Talento Humano y Diseño Organizacional 1. La contribución del Talento Humano como eje vital de la Organización. 2. Tendencias globales que impactan la Gestión Humana y su relación con el Diseño Organizacional. 3. Planeación del Talento Humano para la Organización: 3.1 Aspectos que influyen en la proyección de necesidades de Talento Humano. 3.2. Diseño Ocupacional: Estructura organizacional y análisis y descripción de cargos. Módulo 2: Adquisición, Desarrollo y Retención del Talento 1. La Gestión Humana responsable de impulsar el ciclo de vida del talento en la Organización. 2. Adquisición del Talento: 2.1 Estrategias de Atracción, 2.2 Proceso de reclutamiento y Selección, 2.3 Proceso de Vinculación y Contratación. 3. Desarrollo: 3.1 Onboarding, 3.2 Plan de Carrera, 3.3 Formación y Entrenamiento. 4. Otras estrategias que contribuyen a la Retención: 4.1 Sistemas de Compensación, 4.2 Reconocimiento y Recompensa, 4.3 Creación de ambientes de trabajo positivos para la productividad y el bienestar. 5. Desvinculación Laboral: outplacement como estrategia clave. Módulo 3: Resultados Sostenibles de la Gestión Humana en la Organización 1. El vínculo entre la Gestión del Desempeño y la Satisfacción Laboral. 2. La retroalimentación y la evaluación del desempeño. 3. La medición del clima laboral. 4. Las métricas de la Gestión del Talento Humano. | G20: =+Hoja1!G23
B27: 4. Esquema de Calificación
B28: =+Hoja1!D25 -> Guía (Fase) 1: 15%; Guía (Fase) 2: 25%; Guía (Fase) 3: 15%; Proyecto integrador: 30%; Prueba en línea Unidad de estudio: 15%.
B33: 5. Recursos Tecnológicos (Describir los recursos como software, sala de cómputos, laboratorios) | F33: =+Hoja1!D26 -> 1. Plataforma de aprendizaje en línea. 2. Bases de datos de la biblioteca. 3. Software de gestión de recursos humanos. 4. Herramientas de análisis de datos.
B34: 6. Componente de Lengua extranjera | F34: Inglés | H34: Porcentaje | I34: =+Hoja1!D28 -> 0.2
B35: 7. Bibliografía Obligatoria y Complementaria.
B36: =+Hoja1!E29 -> Bibliografía Obligatoria: Arroyo Tovar, R. (2022). Habilidades Gerenciales : desarrollo de destrezas, competencias y actitud (3a edición.). Ecoe Ediciones. Castillo Aponte, J. Gestión humana integral. La previsión de la fuerza laboral. Ecoe Ediciones, 2020. pp.23 - 36 https://elibro-net.bdbiblioteca.universidadean.edu.co/es/ereader/bibliotecaeanecoe/129215?page=5. Chiavenato, I. (2020). Evaluación de la gestión del talento humano .En Gestión del talento humano: el nuevo papel de los recursos humanos en las organizaciones. (5ª ed., pp. 447 -469) . McGraw-Hill. http://www-ebooks7-24-com.bdbiblioteca.universidadean.edu.co/stage.aspx?il=9350&pg=&ed= Huang, L., Chen, Y., & Wang, J. (2025). Prácticas estratégicas de recursos humanos impulsadas por ESG: Transformación de la gestión de empleados para un crecimiento organizacional sostenible. Cornell University. arXiv. https://arxiv.org/abs/2505.08201 Suárez, P. (2025). Organizaciones basadas en habilidades: el nuevo modelo de gestión del talento humano. Revista Recursos Humanos. https://revistarecursoshumanos.com/gestiontalento/organizaciones-basadas-en-habilidades-el-nuevo-modelo-de-gestion-del-talento-humano/ | F36: =+Hoja1!E30 -> Bibliografía Complementaria: Adaptación digital y cuidado del talento. (2024). Revista Gestión Humana. Deloitte. (2025). Tendencias Globales de Capital Humano 2025. Recursos humanos, fuerza laboral y tendencias en el lugar de trabajo del futuro. Blog Comercial Deloitte. http/www.deloitte.com/latam/es/services/consulting/research/tendencias-globales-de-capital-humano-2025.html Judge, T. A., Piccolo, R. F., Podsakoff, N. P., Shaw, J. C., & Rich, B. L. (2010). La relación entre el salario y la satisfacción laboral: un metaanálisis de la literatura. Journal of Vocational Behavior, 77(2), 157–167. https://doi.org/10.1016/j.jvb.2010.04.002 ManpowerGroup. (2023). Escasez de talento 2023. ManpowerGroup. https://www.manpowergroup.com/ Parra, J. M., Torres, C., & Herrera Sarmiento, E. (2023). ¿Por qué perdemos talento? : cómo gestionar el journey de los colaboradores en la empresa (1a edición.). Ediciones de la U. Pujol-Cols, L. & Lazzaro-Salazar, M. (2022). Gestión de la diversidad en el trabajo. Universidad del Sur (Ed.) Administración de recursos humanos: perspectiva académica y práctica profesional (Edición N.1, pp.155-157). Ediuns. https://www.researchgate.net/publication/365318675_Gestion_de_la_diversidad_en_el_trabajo
B43: 8. Control de Cambios
B44: # versión | C44: Fecha | D44: Elaboró | E44: Revisó | F44: Aprobó | G44: Descripción del cambio
B45: 2 | C45: =+Hoja1!D32 -> 45884 | D45: =+Hoja1!D33 -> SANDRA XIMENA DIAZ | E45: =+Hoja1!D34 -> JOSE DIVITT VELOSA | F45: =+Hoja1!D35 -> Jose Divitt Velosa | G45: =+Hoja1!D36 -> NUEVA MALLA

Sheet Parámetros
A1: Nuclear | B1: FAFCE | C1: 2 | D1: 36 | E1: 60 | F1: Inglés | G1: 0.1 | H1: Posgrado
A2: Transversal | B2: FIN | C2: 3 | D2: 54 | E2: 90 | F2: Alemán | G2: 0.2 | H2: Pregrado
A3: Electiva | B3: FCSH | C3: 4 | D3: 72 | E3: 120 | F3: Italiano | G3: 0.3
A4: Requisito de Grado | B4: EMPRENDIMIENTO | C4: 5 | D4: 90 | E4: 102 | F4: Francés | G4: 0.4
A5: Nuclear / Electiva | B5: INVESTIGACIÓN | C5: 6 | D5: 90 | E5: 150 | F5: Portugués | G5: 0.5
B6: IDIOMAS | C6: 8 | D6: 108 | E6: 180 | G6: 0.6
B7: PRÁCTICA | D7: 144 | E7: 240 | G7: 0.7
B8: CIENCIAS BÁSICAS | D8: 32 | E8: 64 | G8: 0.8
B9: SOCIOHUMANISTICA | D9: 36 | E9: 108 | G9: 0.9
D10: 40 | E10: 152 | G10: 1
D11: 54 | E11: 234
D12: 64 | E12: 320
D13: 24 | E13: 72
D14: 36 | E14: 108
D15: 48 | E15: 144
A25: 45916
